stubbed-0.1.1.dist-info/RECORD
stubbed-0.1.1.dist-info/metadata.json
stubbed-0.1.1.dist-info/WHEEL
stubbed-0.1.1.dist-info/DESCRIPTION.rst
stubbed-0.1.1.dist-info/top_level.txt
stubbed-0.1.1.dist-info/METADATA
stubbed/numpy_stubs.py
stubbed/__init__.py
stubbed/core.py
stubbed/networkx_stubs.py
stubbed/scipy_sparse_stubs.py
stubbed/import_support.py
